bestchoice/__init__.py
best_choice-0.0.1.dist-info/LICENSE
best_choice-0.0.1.dist-info/METADATA
best_choice-0.0.1.dist-info/WHEEL
best_choice-0.0.1.dist-info/top_level.txt
best_choice-0.0.1.dist-info/RECORD
