Metadata-Version: 2.1
Name: best-choice
Version: 0.0.1
Summary: Algorithm for best choice
Home-page: https://github.com/claudiotorresarbe/best-choice
Author: Claudio Torres Arbe
Author-email: claudiotarbe@gmail.com
License: UNKNOWN
Platform: UNKNOWN
Classifier: Programming Language :: Python :: 3.8
Classifier: License :: OSI Approved :: MIT License
Classifier: Operating System :: OS Independent
Requires-Python: >=3.6
